easy_proxy/__init__.py
easy_proxy/proxyes.py
easy_proxy/schedule.py
easy_proxy/setting.py
easy_proxy-0.3.dev1.dist-info/METADATA
easy_proxy-0.3.dev1.dist-info/RECORD
easy_proxy-0.3.dev1.dist-info/WHEEL
easy_proxy-0.3.dev1.dist-info/top_level.txt
