Metadata-Version: 2.1
Name: easy-proxy
Version: 0.3.dev1
Summary: an proxy pool which can easily used
Home-page: https://github.com/sailist/md2latex
Author: hzYang
Author-email: sailist@outlook.com
License: MIT
Keywords: proxy pool
Platform: UNKNOWN
Classifier: Development Status :: 3 - Alpha
Classifier: Intended Audience :: Developers
Classifier: Topic :: Software Development :: Build Tools
Classifier: License :: OSI Approved :: MIT License
Classifier: Programming Language :: Python :: 3
Classifier: Programming Language :: Python :: 3.3
Classifier: Programming Language :: Python :: 3.4
Classifier: Programming Language :: Python :: 3.5
